{
  "annotations": {
    "list": [
      {
        "builtIn": 1,
        "datasource": {
          "type": "grafana",
          "uid": "-- Grafana --"
        },
        "enable": true,
        "hide": true,
        "iconColor": "rgba(0, 211, 255, 1)",
        "name": "Annotations & Alerts",
        "type": "dashboard"
      }
    ]
  },
  "editable": true,
  "fiscalYearStartMonth": 0,
  "graphTooltip": 0,
  "id": null,
  "links": [],
  "panels": [
    {
      "datasource": {
        "type": "prometheus",
        "uid": "prometheus"
      },
      "fieldConfig": {
        "defaults": {
          "color": {
            "mode": "thresholds"
          },
          "thresholds": {
            "mode": "absolute",
            "steps": [
              {
                "color": "green",
                "value": null
              },
              {
                "color": "red",
                "value": 7200
              }
            ]
          },
          "unit": "s"
        },
        "overrides": []
      },
      "gridPos": {
        "h": 4,
        "w": 6,
        "x": 0,
        "y": 0
      },
      "options": {
        "colorMode": "background",
        "graphMode": "none",
        "justifyMode": "auto",
        "orientation": "auto",
        "reduceOptions": {
          "calcs": [
            "lastNotNull"
          ],
          "fields": "",
          "values": false
        },
        "textMode": "value_and_name",
        "wideLayout": true
      },
      "targets": [
        {
          "expr": "time() - max by (run_type) (blocket_scraper_last_activity_unixtime_seconds)",
          "refId": "A",
          "legendFormat": "{{run_type}}"
        }
      ],
      "title": "Time Since Last Scrape Activity",
      "type": "stat"
    },
    {
      "datasource": {
        "type": "prometheus",
        "uid": "prometheus"
      },
      "fieldConfig": {
        "defaults": {
          "color": {
            "mode": "thresholds"
          },
          "thresholds": {
            "mode": "absolute",
            "steps": [
              {
                "color": "red",
                "value": null
              },
              {
                "color": "green",
                "value": 1
              }
            ]
          }
        },
        "overrides": []
      },
      "gridPos": {
        "h": 4,
        "w": 6,
        "x": 6,
        "y": 0
      },
      "options": {
        "colorMode": "background",
        "graphMode": "none",
        "justifyMode": "auto",
        "orientation": "auto",
        "reduceOptions": {
          "calcs": [
            "lastNotNull"
          ],
          "fields": "",
          "values": false
        },
        "textMode": "value_and_name",
        "wideLayout": true
      },
      "targets": [
        {
          "expr": "max by (run_type) (blocket_scraper_last_listings_scraped)",
          "refId": "A",
          "legendFormat": "{{run_type}}"
        }
      ],
      "title": "Last Listings Scraped",
      "type": "stat"
    },
    {
      "datasource": {
        "type": "prometheus",
        "uid": "prometheus"
      },
      "fieldConfig": {
        "defaults": {
          "color": {
            "mode": "palette-classic"
          },
          "unit": "s"
        },
        "overrides": []
      },
      "gridPos": {
        "h": 4,
        "w": 6,
        "x": 12,
        "y": 0
      },
      "options": {
        "colorMode": "value",
        "graphMode": "area",
        "justifyMode": "auto",
        "orientation": "auto",
        "reduceOptions": {
          "calcs": [
            "lastNotNull"
          ],
          "fields": "",
          "values": false
        },
        "textMode": "value_and_name",
        "wideLayout": true
      },
      "targets": [
        {
          "expr": "max by (run_type) (blocket_scraper_last_run_duration_seconds)",
          "refId": "A",
          "legendFormat": "{{run_type}}"
        }
      ],
      "title": "Last Scrape Duration",
      "type": "stat"
    },
    {
      "datasource": {
        "type": "prometheus",
        "uid": "prometheus"
      },
      "fieldConfig": {
        "defaults": {
          "color": {
            "mode": "thresholds"
          },
          "thresholds": {
            "mode": "absolute",
            "steps": [
              {
                "color": "green",
                "value": null
              },
              {
                "color": "orange",
                "value": 1
              },
              {
                "color": "red",
                "value": 10
              }
            ]
          }
        },
        "overrides": []
      },
      "gridPos": {
        "h": 4,
        "w": 6,
        "x": 18,
        "y": 0
      },
      "options": {
        "colorMode": "background",
        "graphMode": "none",
        "justifyMode": "auto",
        "orientation": "auto",
        "reduceOptions": {
          "calcs": [
            "lastNotNull"
          ],
          "fields": "",
          "values": false
        },
        "textMode": "value_and_name",
        "wideLayout": true
      },
      "targets": [
        {
          "expr": "max by (run_type) (blocket_scraper_last_detail_rejected)",
          "refId": "A",
          "legendFormat": "{{run_type}}"
        }
      ],
      "title": "Last Detail Rejected",
      "type": "stat"
    },
    {
      "datasource": {
        "type": "prometheus",
        "uid": "prometheus"
      },
      "fieldConfig": {
        "defaults": {
          "color": {
            "mode": "palette-classic"
          },
          "unit": "short"
        },
        "overrides": []
      },
      "gridPos": {
        "h": 8,
        "w": 24,
        "x": 0,
        "y": 4
      },
      "options": {
        "legend": {
          "calcs": [],
          "displayMode": "table",
          "placement": "bottom",
          "showLegend": true
        },
        "tooltip": {
          "mode": "multi",
          "sort": "none"
        }
      },
      "targets": [
        {
          "expr": "sum by (route) (increase(blocket_api_http_requests_total[5m]))",
          "legendFormat": "{{route}}",
          "refId": "A"
        }
      ],
      "title": "API Requests (5m)",
      "type": "timeseries"
    },
    {
      "datasource": {
        "type": "prometheus",
        "uid": "prometheus"
      },
      "fieldConfig": {
        "defaults": {
          "color": {
            "mode": "palette-classic"
          },
          "unit": "s"
        },
        "overrides": []
      },
      "gridPos": {
        "h": 8,
        "w": 12,
        "x": 0,
        "y": 12
      },
      "options": {
        "legend": {
          "calcs": [],
          "displayMode": "table",
          "placement": "bottom",
          "showLegend": true
        },
        "tooltip": {
          "mode": "multi",
          "sort": "none"
        }
      },
      "targets": [
        {
          "expr": "time() - max by (run_type) (blocket_scraper_last_success_unixtime_seconds)",
          "legendFormat": "{{run_type}} success",
          "refId": "A"
        },
        {
          "expr": "time() - max by (run_type) (blocket_scraper_last_failure_unixtime_seconds)",
          "legendFormat": "{{run_type}} failure",
          "refId": "B"
        }
      ],
      "title": "Time Since Last Success/Failure",
      "type": "timeseries"
    },
    {
      "datasource": {
        "type": "prometheus",
        "uid": "prometheus"
      },
      "fieldConfig": {
        "defaults": {
          "color": {
            "mode": "palette-classic"
          },
          "unit": "short"
        },
        "overrides": []
      },
      "gridPos": {
        "h": 8,
        "w": 12,
        "x": 12,
        "y": 12
      },
      "options": {
        "legend": {
          "calcs": [],
          "displayMode": "table",
          "placement": "bottom",
          "showLegend": true
        },
        "tooltip": {
          "mode": "multi",
          "sort": "none"
        }
      },
      "targets": [
        {
          "expr": "sum by (run_type, phase) (increase(blocket_scraper_requests_total[5m]))",
          "legendFormat": "{{run_type}} {{phase}} requests",
          "refId": "A"
        },
        {
          "expr": "sum by (run_type) (increase(blocket_scraper_retries_total[5m]))",
          "legendFormat": "{{run_type}} retries",
          "refId": "B"
        }
      ],
      "title": "Scraper Requests and Retries (5m)",
      "type": "timeseries"
    },
    {
      "datasource": {
        "type": "prometheus",
        "uid": "prometheus"
      },
      "fieldConfig": {
        "defaults": {
          "color": {
            "mode": "palette-classic"
          },
          "unit": "short"
        },
        "overrides": []
      },
      "gridPos": {
        "h": 8,
        "w": 12,
        "x": 0,
        "y": 20
      },
      "options": {
        "legend": {
          "calcs": [],
          "displayMode": "table",
          "placement": "bottom",
          "showLegend": true
        },
        "tooltip": {
          "mode": "multi",
          "sort": "none"
        }
      },
      "targets": [
        {
          "expr": "max by (run_type) (blocket_scraper_last_listings_discovered)",
          "legendFormat": "{{run_type}} discovered",
          "refId": "A"
        },
        {
          "expr": "max by (run_type) (blocket_scraper_last_listings_created)",
          "legendFormat": "{{run_type}} created",
          "refId": "B"
        },
        {
          "expr": "max by (run_type) (blocket_scraper_last_listings_changed)",
          "legendFormat": "{{run_type}} changed",
          "refId": "C"
        },
        {
          "expr": "max by (run_type) (blocket_scraper_last_listings_unchanged)",
          "legendFormat": "{{run_type}} unchanged",
          "refId": "D"
        }
      ],
      "title": "Last Run Listing Outcomes",
      "type": "timeseries"
    },
    {
      "datasource": {
        "type": "prometheus",
        "uid": "prometheus"
      },
      "fieldConfig": {
        "defaults": {
          "color": {
            "mode": "palette-classic"
          },
          "unit": "short"
        },
        "overrides": []
      },
      "gridPos": {
        "h": 8,
        "w": 12,
        "x": 12,
        "y": 20
      },
      "options": {
        "legend": {
          "calcs": [],
          "displayMode": "table",
          "placement": "bottom",
          "showLegend": true
        },
        "tooltip": {
          "mode": "multi",
          "sort": "none"
        }
      },
      "targets": [
        {
          "expr": "max by (run_type) (blocket_scraper_last_detail_failures)",
          "legendFormat": "{{run_type}} failures",
          "refId": "A"
        },
        {
          "expr": "max by (run_type) (blocket_scraper_last_detail_fallbacks)",
          "legendFormat": "{{run_type}} fallbacks",
          "refId": "B"
        },
        {
          "expr": "max by (run_type) (blocket_scraper_last_detail_rejected)",
          "legendFormat": "{{run_type}} rejected",
          "refId": "C"
        }
      ],
      "title": "Last Run Detail Quality",
      "type": "timeseries"
    },
    {
      "datasource": {
        "type": "prometheus",
        "uid": "prometheus"
      },
      "fieldConfig": {
        "defaults": {
          "color": {
            "mode": "palette-classic"
          },
          "unit": "short"
        },
        "overrides": []
      },
      "gridPos": {
        "h": 8,
        "w": 12,
        "x": 0,
        "y": 28
      },
      "options": {
        "legend": {
          "calcs": [],
          "displayMode": "table",
          "placement": "bottom",
          "showLegend": true
        },
        "tooltip": {
          "mode": "multi",
          "sort": "none"
        }
      },
      "targets": [
        {
          "expr": "sum by (run_type) (increase(blocket_scraper_images_seen_total[30m]))",
          "legendFormat": "{{run_type}} seen",
          "refId": "A"
        },
        {
          "expr": "sum by (run_type) (increase(blocket_scraper_images_downloaded_total[30m]))",
          "legendFormat": "{{run_type}} downloaded",
          "refId": "B"
        },
        {
          "expr": "sum by (run_type) (increase(blocket_scraper_images_reused_total[30m]))",
          "legendFormat": "{{run_type}} reused",
          "refId": "C"
        },
        {
          "expr": "sum by (run_type) (increase(blocket_scraper_images_failed_total[30m]))",
          "legendFormat": "{{run_type}} failed",
          "refId": "D"
        }
      ],
      "title": "Image Processing (30m)",
      "type": "timeseries"
    },
    {
      "datasource": {
        "type": "prometheus",
        "uid": "prometheus"
      },
      "fieldConfig": {
        "defaults": {
          "color": {
            "mode": "palette-classic"
          },
          "unit": "short"
        },
        "overrides": []
      },
      "gridPos": {
        "h": 8,
        "w": 12,
        "x": 12,
        "y": 28
      },
      "options": {
        "legend": {
          "calcs": [],
          "displayMode": "table",
          "placement": "bottom",
          "showLegend": true
        },
        "tooltip": {
          "mode": "multi",
          "sort": "none"
        }
      },
      "targets": [
        {
          "expr": "sum by (run_type) (increase(blocket_scraper_neo4j_ingest_processed_total[30m]))",
          "legendFormat": "{{run_type}} processed",
          "refId": "A"
        },
        {
          "expr": "sum by (run_type) (increase(blocket_scraper_neo4j_ingest_upserted_total[30m]))",
          "legendFormat": "{{run_type}} upserted",
          "refId": "B"
        },
        {
          "expr": "sum by (run_type) (increase(blocket_scraper_neo4j_ingest_created_total[30m]))",
          "legendFormat": "{{run_type}} created",
          "refId": "C"
        },
        {
          "expr": "sum by (run_type) (increase(blocket_scraper_neo4j_ingest_changed_total[30m]))",
          "legendFormat": "{{run_type}} changed",
          "refId": "D"
        }
      ],
      "title": "Neo4j Ingest (30m)",
      "type": "timeseries"
    }
  ],
  "refresh": "30s",
  "schemaVersion": 41,
  "style": "dark",
  "tags": [
    "homelab",
    "blocket"
  ],
  "templating": {
    "list": []
  },
  "time": {
    "from": "now-24h",
    "to": "now"
  },
  "timepicker": {},
  "timezone": "",
  "title": "Blocket Overview",
  "uid": "blocket-overview",
  "version": 1,
  "weekStart": ""
}
